<Properties StartupConfiguration="{1039C66A-AC09-4DA9-B829-833C36BF091B}|Default">
  <MonoDevelop.Ide.ItemProperties.CalculatorAPI PreferredExecutionTarget="/Applications/Safari.app" />
  <MonoDevelop.Ide.ItemProperties.CalculatorTest PreferredExecutionTarget="MonoDevelop.Default" />
  <MultiItemStartupConfigurations />
  <MonoDevelop.Ide.DebuggingService.PinnedWatches />
  <MonoDevelop.Ide.DebuggingService.Breakpoints>
    <BreakpointStore />
  </MonoDevelop.Ide.DebuggingService.Breakpoints>
  <MonoDevelop.Ide.Workbench ActiveDocument="UnitTest1.cs">
    <Files>
      <File FileName="../CalculatorAPI/Controllers/CalculatorController.cs" Line="58" Column="88" />
      <File FileName="UnitTest1.cs" Line="251" Column="75" />
      <File FileName="../CalculatorLogic/Calculator.cs" Line="5" Column="31" />
      <File FileName="../CalculatorAPI/Program.cs" Line="1" Column="1" />
      <File FileName="Usings.cs" Line="1" Column="1" />
    </Files>
    <Pads>
      <Pad Id="ProjectPad">
        <State name="__root__">
          <Node name="CalculatorTest" expanded="True">
            <Node name="CalculatorAPI" expanded="True">
              <Node name="Controllers" expanded="True" />
            </Node>
            <Node name="CalculatorLogic" expanded="True" />
            <Node name="CalculatorTest" expanded="True">
              <Node name="UnitTest1.cs" selected="True" />
            </Node>
          </Node>
        </State>
      </Pad>
      <Pad Id="MonoDevelop.Debugger.WatchPad">
        <State />
      </Pad>
      <Pad Id="MonoDevelop.UnitTesting.TestPad">
        <State name="__root__">
          <Node name="CalculatorTest" expanded="True" selected="True" />
        </State>
      </Pad>
    </Pads>
  </MonoDevelop.Ide.Workbench>
  <MonoDevelop.Ide.Workspace ActiveConfiguration="Debug" />
</Properties>